{"elapsed":"0.231","endpoint-url":"https://raw.githubusercontent.com/digital-land/development-plan-type-collection/main/data/development-plan-type.csv","entry-date":"2021-07-31T00:30:55.066466","request-headers":{"Accept":"*/*","Accept-Encoding":"gzip, deflate","Connection":"keep-alive","User-Agent":"Digital Land"},"resource":"d4cd3017668c5548df11cecd4345cee90e81cf3b6e98ebab0cab61dac82e748d","response-headers":{"Accept-Ranges":"bytes","Access-Control-Allow-Origin":"*","Cache-Control":"max-age=300","Connection":"keep-alive","Content-Encoding":"gzip","Content-Length":"325","Content-Security-Policy":"default-src 'none'; style-src 'unsafe-inline'; sandbox","Content-Type":"text/plain; charset=utf-8","Date":"Sat, 31 Jul 2021 00:30:56 GMT","ETag":"W/\"8e7dbff56b7412b75eb6eeced9348674d0529ab7605aaf4453ec54425ca00807\"","Expires":"Sat, 31 Jul 2021 00:35:56 GMT","Source-Age":"0","Strict-Transport-Security":"max-age=31536000","Vary":"Authorization,Accept-Encoding","Via":"1.1 varnish","X-Cache":"MISS","X-Cache-Hits":"0","X-Content-Type-Options":"nosniff","X-Fastly-Request-ID":"75b2ef3d7d50c3105f10ae45be5841059d015ccb","X-Frame-Options":"deny","X-GitHub-Request-Id":"CA26:3C52:5747B4:81B0DE:610499C0","X-Served-By":"cache-sea4466-SEA","X-Timer":"S1627691456.971596,VS0,VE195","X-XSS-Protection":"1; mode=block"},"ssl-verify":true,"status":"200"}